brkraw_mrs/__init__.py
brkraw_mrs/brkraw_hook.yaml
brkraw_mrs/hook.py
brkraw_mrs/ui.py
brkraw_mrs/viewer_hook.py
brkraw_mrs/docs/hook.md
brkraw_mrs/rules/mrs.yaml
brkraw_mrs/specs/info_spec.yaml
brkraw_mrs/specs/metadata_spec.yaml
brkraw_mrs/transforms/__init__.py
brkraw_mrs/transforms/mrs.py
brkraw_mrs-0.2.3.dist-info/licenses/LICENSE
brkraw_mrs-0.2.3.dist-info/licenses/NOTICE
brkraw_mrs-0.2.3.dist-info/METADATA
brkraw_mrs-0.2.3.dist-info/WHEEL
brkraw_mrs-0.2.3.dist-info/entry_points.txt
brkraw_mrs-0.2.3.dist-info/top_level.txt
brkraw_mrs-0.2.3.dist-info/RECORD
