Metadata-Version: 2.4
Name: brkraw-mrs
Version: 0.2.3
Summary: BrkRaw converter hook for Bruker PRESS SVS NIfTI-MRS outputs (ported from spec2nii)
Author: BrkRaw contributors
License: MIT
Requires-Python: >=3.9
License-File: LICENSE
License-File: NOTICE
Requires-Dist: brkraw
Requires-Dist: numpy
Requires-Dist: nibabel
Requires-Dist: nifti-mrs
Provides-Extra: dev
Requires-Dist: packaging; extra == "dev"
Requires-Dist: tomli; python_version < "3.11" and extra == "dev"
Dynamic: license-file
